{"nodes": [{"id": "d_ai_projects_open_cli_tests_extensions_test_mcp_py", "label": "test_mcp.py", "file_type": "code", "source_file": "D:\\AI_Projects\\open-cli\\tests\\extensions\\test_mcp.py", "source_location": "L1"}, {"id": "extensions_test_mcp_testmcptool", "label": "TestMCPTool", "file_type": "code", "source_file": "D:\\AI_Projects\\open-cli\\tests\\extensions\\test_mcp.py", "source_location": "L10"}, {"id": "extensions_test_mcp_testmcptool_test_tool_definition", "label": ".test_tool_definition()", "file_type": "code", "source_file": "D:\\AI_Projects\\open-cli\\tests\\extensions\\test_mcp.py", "source_location": "L11"}, {"id": "extensions_test_mcp_test_execute_without_session", "label": "test_execute_without_session()", "file_type": "code", "source_file": "D:\\AI_Projects\\open-cli\\tests\\extensions\\test_mcp.py", "source_location": "L19"}, {"id": "extensions_test_mcp_test_execute_with_mock_session", "label": "test_execute_with_mock_session()", "file_type": "code", "source_file": "D:\\AI_Projects\\open-cli\\tests\\extensions\\test_mcp.py", "source_location": "L26"}], "edges": [{"source": "d_ai_projects_open_cli_tests_extensions_test_mcp_py", "target": "sys", "relation": "imports", "context": "import", "confidence": "EXTRACTED", "source_file": "D:\\AI_Projects\\open-cli\\tests\\extensions\\test_mcp.py", "source_location": "L1", "weight": 1.0}, {"source": "d_ai_projects_open_cli_tests_extensions_test_mcp_py", "target": "pathlib", "relation": "imports_from", "context": "import", "confidence": "EXTRACTED", "source_file": "D:\\AI_Projects\\open-cli\\tests\\extensions\\test_mcp.py", "source_location": "L2", "weight": 1.0}, {"source": "d_ai_projects_open_cli_tests_extensions_test_mcp_py", "target": "pytest", "relation": "imports", "context": "import", "confidence": "EXTRACTED", "source_file": "D:\\AI_Projects\\open-cli\\tests\\extensions\\test_mcp.py", "source_location": "L5", "weight": 1.0}, {"source": "d_ai_projects_open_cli_tests_extensions_test_mcp_py", "target": "unittest_mock", "relation": "imports_from", "context": "import", "confidence": "EXTRACTED", "source_file": "D:\\AI_Projects\\open-cli\\tests\\extensions\\test_mcp.py", "source_location": "L6", "weight": 1.0}, {"source": "d_ai_projects_open_cli_tests_extensions_test_mcp_py", "target": "opencli_extensions_mcp_tools", "relation": "imports_from", "context": "import", "confidence": "EXTRACTED", "source_file": "D:\\AI_Projects\\open-cli\\tests\\extensions\\test_mcp.py", "source_location": "L7", "weight": 1.0}, {"source": "d_ai_projects_open_cli_tests_extensions_test_mcp_py", "target": "opencli_tools_base", "relation": "imports_from", "context": "import", "confidence": "EXTRACTED", "source_file": "D:\\AI_Projects\\open-cli\\tests\\extensions\\test_mcp.py", "source_location": "L8", "weight": 1.0}, {"source": "d_ai_projects_open_cli_tests_extensions_test_mcp_py", "target": "extensions_test_mcp_testmcptool", "relation": "contains", "confidence": "EXTRACTED", "source_file": "D:\\AI_Projects\\open-cli\\tests\\extensions\\test_mcp.py", "source_location": "L10", "weight": 1.0}, {"source": "extensions_test_mcp_testmcptool", "target": "extensions_test_mcp_testmcptool_test_tool_definition", "relation": "method", "confidence": "EXTRACTED", "source_file": "D:\\AI_Projects\\open-cli\\tests\\extensions\\test_mcp.py", "source_location": "L11", "weight": 1.0}, {"source": "d_ai_projects_open_cli_tests_extensions_test_mcp_py", "target": "extensions_test_mcp_test_execute_without_session", "relation": "contains", "confidence": "EXTRACTED", "source_file": "D:\\AI_Projects\\open-cli\\tests\\extensions\\test_mcp.py", "source_location": "L19", "weight": 1.0}, {"source": "d_ai_projects_open_cli_tests_extensions_test_mcp_py", "target": "extensions_test_mcp_test_execute_with_mock_session", "relation": "contains", "confidence": "EXTRACTED", "source_file": "D:\\AI_Projects\\open-cli\\tests\\extensions\\test_mcp.py", "source_location": "L26", "weight": 1.0}], "raw_calls": [{"caller_nid": "extensions_test_mcp_testmcptool_test_tool_definition", "callee": "MCPTool", "is_member_call": false, "source_file": "D:\\AI_Projects\\open-cli\\tests\\extensions\\test_mcp.py", "source_location": "L12"}, {"caller_nid": "extensions_test_mcp_testmcptool_test_tool_definition", "callee": "get_definition", "is_member_call": true, "source_file": "D:\\AI_Projects\\open-cli\\tests\\extensions\\test_mcp.py", "source_location": "L13"}, {"caller_nid": "extensions_test_mcp_test_execute_without_session", "callee": "MCPTool", "is_member_call": false, "source_file": "D:\\AI_Projects\\open-cli\\tests\\extensions\\test_mcp.py", "source_location": "L20"}, {"caller_nid": "extensions_test_mcp_test_execute_without_session", "callee": "execute", "is_member_call": true, "source_file": "D:\\AI_Projects\\open-cli\\tests\\extensions\\test_mcp.py", "source_location": "L21"}, {"caller_nid": "extensions_test_mcp_test_execute_with_mock_session", "callee": "MCPTool", "is_member_call": false, "source_file": "D:\\AI_Projects\\open-cli\\tests\\extensions\\test_mcp.py", "source_location": "L27"}, {"caller_nid": "extensions_test_mcp_test_execute_with_mock_session", "callee": "AsyncMock", "is_member_call": false, "source_file": "D:\\AI_Projects\\open-cli\\tests\\extensions\\test_mcp.py", "source_location": "L28"}, {"caller_nid": "extensions_test_mcp_test_execute_with_mock_session", "callee": "AsyncMock", "is_member_call": false, "source_file": "D:\\AI_Projects\\open-cli\\tests\\extensions\\test_mcp.py", "source_location": "L29"}, {"caller_nid": "extensions_test_mcp_test_execute_with_mock_session", "callee": "AsyncMock", "is_member_call": false, "source_file": "D:\\AI_Projects\\open-cli\\tests\\extensions\\test_mcp.py", "source_location": "L31"}, {"caller_nid": "extensions_test_mcp_test_execute_with_mock_session", "callee": "execute", "is_member_call": true, "source_file": "D:\\AI_Projects\\open-cli\\tests\\extensions\\test_mcp.py", "source_location": "L33"}, {"caller_nid": "extensions_test_mcp_test_execute_with_mock_session", "callee": "assert_called_once_with", "is_member_call": true, "source_file": "D:\\AI_Projects\\open-cli\\tests\\extensions\\test_mcp.py", "source_location": "L36"}]}