{"nodes": [{"id": "d_ai_projects_open_cli_tests_core_test_session_py", "label": "test_session.py", "file_type": "code", "source_file": "D:\\AI_Projects\\open-cli\\tests\\core\\test_session.py", "source_location": "L1"}, {"id": "core_test_session_temp_session_dir", "label": "temp_session_dir()", "file_type": "code", "source_file": "D:\\AI_Projects\\open-cli\\tests\\core\\test_session.py", "source_location": "L8"}, {"id": "core_test_session_test_session_manager_init", "label": "test_session_manager_init()", "file_type": "code", "source_file": "D:\\AI_Projects\\open-cli\\tests\\core\\test_session.py", "source_location": "L13"}, {"id": "core_test_session_test_create_session", "label": "test_create_session()", "file_type": "code", "source_file": "D:\\AI_Projects\\open-cli\\tests\\core\\test_session.py", "source_location": "L17"}, {"id": "core_test_session_test_save_and_load_session", "label": "test_save_and_load_session()", "file_type": "code", "source_file": "D:\\AI_Projects\\open-cli\\tests\\core\\test_session.py", "source_location": "L24"}, {"id": "core_test_session_test_list_sessions", "label": "test_list_sessions()", "file_type": "code", "source_file": "D:\\AI_Projects\\open-cli\\tests\\core\\test_session.py", "source_location": "L33"}], "edges": [{"source": "d_ai_projects_open_cli_tests_core_test_session_py", "target": "pytest", "relation": "imports", "context": "import", "confidence": "EXTRACTED", "source_file": "D:\\AI_Projects\\open-cli\\tests\\core\\test_session.py", "source_location": "L1", "weight": 1.0}, {"source": "d_ai_projects_open_cli_tests_core_test_session_py", "target": "tempfile", "relation": "imports", "context": "import", "confidence": "EXTRACTED", "source_file": "D:\\AI_Projects\\open-cli\\tests\\core\\test_session.py", "source_location": "L2", "weight": 1.0}, {"source": "d_ai_projects_open_cli_tests_core_test_session_py", "target": "shutil", "relation": "imports", "context": "import", "confidence": "EXTRACTED", "source_file": "D:\\AI_Projects\\open-cli\\tests\\core\\test_session.py", "source_location": "L3", "weight": 1.0}, {"source": "d_ai_projects_open_cli_tests_core_test_session_py", "target": "pathlib", "relation": "imports_from", "context": "import", "confidence": "EXTRACTED", "source_file": "D:\\AI_Projects\\open-cli\\tests\\core\\test_session.py", "source_location": "L4", "weight": 1.0}, {"source": "d_ai_projects_open_cli_tests_core_test_session_py", "target": "opencli_server_session", "relation": "imports_from", "context": "import", "confidence": "EXTRACTED", "source_file": "D:\\AI_Projects\\open-cli\\tests\\core\\test_session.py", "source_location": "L5", "weight": 1.0}, {"source": "d_ai_projects_open_cli_tests_core_test_session_py", "target": "core_test_session_temp_session_dir", "relation": "contains", "confidence": "EXTRACTED", "source_file": "D:\\AI_Projects\\open-cli\\tests\\core\\test_session.py", "source_location": "L8", "weight": 1.0}, {"source": "d_ai_projects_open_cli_tests_core_test_session_py", "target": "core_test_session_test_session_manager_init", "relation": "contains", "confidence": "EXTRACTED", "source_file": "D:\\AI_Projects\\open-cli\\tests\\core\\test_session.py", "source_location": "L13", "weight": 1.0}, {"source": "d_ai_projects_open_cli_tests_core_test_session_py", "target": "core_test_session_test_create_session", "relation": "contains", "confidence": "EXTRACTED", "source_file": "D:\\AI_Projects\\open-cli\\tests\\core\\test_session.py", "source_location": "L17", "weight": 1.0}, {"source": "d_ai_projects_open_cli_tests_core_test_session_py", "target": "core_test_session_test_save_and_load_session", "relation": "contains", "confidence": "EXTRACTED", "source_file": "D:\\AI_Projects\\open-cli\\tests\\core\\test_session.py", "source_location": "L24", "weight": 1.0}, {"source": "d_ai_projects_open_cli_tests_core_test_session_py", "target": "core_test_session_test_list_sessions", "relation": "contains", "confidence": "EXTRACTED", "source_file": "D:\\AI_Projects\\open-cli\\tests\\core\\test_session.py", "source_location": "L33", "weight": 1.0}], "raw_calls": [{"caller_nid": "core_test_session_temp_session_dir", "callee": "mkdtemp", "is_member_call": true, "source_file": "D:\\AI_Projects\\open-cli\\tests\\core\\test_session.py", "source_location": "L9"}, {"caller_nid": "core_test_session_temp_session_dir", "callee": "Path", "is_member_call": false, "source_file": "D:\\AI_Projects\\open-cli\\tests\\core\\test_session.py", "source_location": "L10"}, {"caller_nid": "core_test_session_temp_session_dir", "callee": "rmtree", "is_member_call": true, "source_file": "D:\\AI_Projects\\open-cli\\tests\\core\\test_session.py", "source_location": "L11"}, {"caller_nid": "core_test_session_test_session_manager_init", "callee": "SessionManager", "is_member_call": false, "source_file": "D:\\AI_Projects\\open-cli\\tests\\core\\test_session.py", "source_location": "L14"}, {"caller_nid": "core_test_session_test_create_session", "callee": "SessionManager", "is_member_call": false, "source_file": "D:\\AI_Projects\\open-cli\\tests\\core\\test_session.py", "source_location": "L18"}, {"caller_nid": "core_test_session_test_create_session", "callee": "create_session", "is_member_call": true, "source_file": "D:\\AI_Projects\\open-cli\\tests\\core\\test_session.py", "source_location": "L19"}, {"caller_nid": "core_test_session_test_save_and_load_session", "callee": "SessionManager", "is_member_call": false, "source_file": "D:\\AI_Projects\\open-cli\\tests\\core\\test_session.py", "source_location": "L25"}, {"caller_nid": "core_test_session_test_save_and_load_session", "callee": "create_session", "is_member_call": true, "source_file": "D:\\AI_Projects\\open-cli\\tests\\core\\test_session.py", "source_location": "L26"}, {"caller_nid": "core_test_session_test_save_and_load_session", "callee": "save_session", "is_member_call": true, "source_file": "D:\\AI_Projects\\open-cli\\tests\\core\\test_session.py", "source_location": "L27"}, {"caller_nid": "core_test_session_test_save_and_load_session", "callee": "load_session", "is_member_call": true, "source_file": "D:\\AI_Projects\\open-cli\\tests\\core\\test_session.py", "source_location": "L29"}, {"caller_nid": "core_test_session_test_list_sessions", "callee": "SessionManager", "is_member_call": false, "source_file": "D:\\AI_Projects\\open-cli\\tests\\core\\test_session.py", "source_location": "L34"}, {"caller_nid": "core_test_session_test_list_sessions", "callee": "create_session", "is_member_call": true, "source_file": "D:\\AI_Projects\\open-cli\\tests\\core\\test_session.py", "source_location": "L35"}, {"caller_nid": "core_test_session_test_list_sessions", "callee": "create_session", "is_member_call": true, "source_file": "D:\\AI_Projects\\open-cli\\tests\\core\\test_session.py", "source_location": "L36"}, {"caller_nid": "core_test_session_test_list_sessions", "callee": "list_sessions", "is_member_call": true, "source_file": "D:\\AI_Projects\\open-cli\\tests\\core\\test_session.py", "source_location": "L37"}, {"caller_nid": "core_test_session_test_list_sessions", "callee": "len", "is_member_call": false, "source_file": "D:\\AI_Projects\\open-cli\\tests\\core\\test_session.py", "source_location": "L38"}]}